synop2bufr/__init__.py
synop2bufr/cli.py
synop2bufr/resources/synop-mappings-307080.json
synop2bufr/resources/synop-mappings-307096.json
synop2bufr-0.7.0.dist-info/LICENSE
synop2bufr-0.7.0.dist-info/METADATA
synop2bufr-0.7.0.dist-info/WHEEL
synop2bufr-0.7.0.dist-info/entry_points.txt
synop2bufr-0.7.0.dist-info/top_level.txt
synop2bufr-0.7.0.dist-info/RECORD
