Metadata-Version: 2.1
Name: synop2bufr
Version: 0.7.0
Summary: Convert a SYNOP TAC messages or a SYNOP file to BUFR4.
Author: Rory Burke
Author-email: RBurke@wmo.int
Maintainer: David I. Berry
Maintainer-email: DBerry@wmo.int
License: Apache Software License
Keywords: WMO SYNOP BUFR decoding weather observations
Platform: all
Classifier: Development Status :: 3 - Alpha
Classifier: Environment :: Console
Classifier: Intended Audience :: Developers
Classifier: Intended Audience :: Science/Research
Classifier: License :: OSI Approved :: Apache Software License
Classifier: Operating System :: OS Independent
Classifier: Programming Language :: Python
Classifier: Topic :: Scientific/Engineering
License-File: LICENSE
Requires-Dist: click
Requires-Dist: pymetdecoder-wmo
Requires-Dist: csv2bufr
